[
    { "id": 0, "name": "Forgetfulness Memory Loss" },
    { "id": 1, "name": "Headache" },
    { "id": 2, "name": "Hair Loss" },
    { "id": 3, "name": "Dry Eyes and Mouth" },
    { "id": 4, "name": "Eye Discharge" },
    { "id": 5, "name": "Pain in the Eye" },
    { "id": 6, "name": "Sore Throat" },
    { "id": 7, "name": "Dry Mouth and Excessive Thirst" },
    { "id": 8, "name": "Dry Skin" },
    { "id": 9, "name": "Chest Pain" },
    { "id": 10, "name": "Coughs and Colds" },
    { "id": 11, "name": "Heart Palpitations" },
    { "id": 12, "name": "Elbow Pain" },
    { "id": 13, "name": "Hand Pain" },
    { "id": 14, "name": "Nail Problems" },
    { "id": 15, "name": "Acid Reflux Treatment" },
    { "id": 16, "name": "Diarrhea" },
    { "id": 17, "name": "Colon Cancer Screening" },
    { "id": 18, "name": "Ankle Pain" },
    { "id": 19, "name": "Foot Pain" },
    { "id": 20, "name": "Hip Pain" },
    { "id": 21, "name": "skin" },
    {"id": 22, "name": "general"}
]
